<?xml version="1.0" encoding="utf-8"?>
<SoundBanksInfo Platform="Windows" BasePlatform="Windows" SchemaVersion="16" SoundBankVersion="150">
	<SoundBanks>
		<SoundBank Id="2739294108" Type="Event" GUID="{F4781E7D-6509-47BA-A5C1-2D17C7539C1C}" Language="SFX" Hash="{50E3FE36-5150-60B7-CB5B-DA8B3925E4DE}">
			<ObjectPath>Play_SFX_ALIEN_TELEPORTED</ObjectPath>
			<ShortName>Play_SFX_ALIEN_TELEPORTED</ShortName>
			<Path>Event/Play_SFX_ALIEN_TELEPORTED.bnk</Path>
			<Media>
				<File Id="1062678991" Language="SFX" Streaming="false" Location="Loose">
					<ShortName>SFX_ALIEN_TELEPORTED.wav</ShortName>
					<Path>Media/1062678991.wem</Path>
					<CachePath>SFX/SFX_ALIEN_TELEPORTED_818F3B66.wem</CachePath>
				</File>
			</Media>
			<Events>
				<Event Id="2739294108" Name="Play_SFX_ALIEN_TELEPORTED" ObjectPath="\Events\Default Work Unit\ALIEN 1\Play_SFX_ALIEN_TELEPORTED" GUID="{F4781E7D-6509-47BA-A5C1-2D17C7539C1C}" DurationType="OneShot" DurationMin="4" DurationMax="4">
					<MediaRefs>
						<MediaRef Id="1062678991"/>
					</MediaRefs>
				</Event>
			</Events>
		</SoundBank>
	</SoundBanks>
	<FileHash>{9D63C82F-15E8-69B7-F969-685014819013}</FileHash>
</SoundBanksInfo>
